{
  "name": "Basic Pod",
  "id": "io.kubeshop.monokle.templates.default.basic-pod-template",
  "author": "kubeshop.io",
  "version": "1.0.0",
  "description": "Creates a Pod for a specified Image",
  "repository" : "",
  "type": "vanilla",
  "icon": "basic_pod.svg",
  "forms": [
    {
      "name": "Pod Settings",
      "description": "Specify the Image to use",
      "schema": "form-schema.json",
      "uiSchema": "form-ui-schema.json"
    }
  ],
  "manifests": [
    {
      "filePath": "template.yaml"
    }
  ],
  "resultMessage": "Pod resource created successfully!",
  "helpUrl": "https://github.com/kubeshop/monokle-default-templates-plugin"
}
